geofetch/__init__.py
geofetch/__main__.py
geofetch/_version.py
geofetch/cli.py
geofetch/const.py
geofetch/finder.py
geofetch/geofetch.py
geofetch/sraconvert.py
geofetch/utils.py
geofetch/templates/config_processed_template.yaml
geofetch/templates/config_template.yaml
geofetch/templates/looper_config_template.yaml
geofetch/templates/looper_sra_convert.yaml
geofetch/templates/pipeline_interface_convert.yaml
geofetch/templates/resources.tsv
geofetch/templates/sra_convert_schema.yaml
geofetch-0.12.8.dist-info/licenses/LICENSE.txt
geofetch-0.12.8.dist-info/METADATA
geofetch-0.12.8.dist-info/WHEEL
geofetch-0.12.8.dist-info/entry_points.txt
geofetch-0.12.8.dist-info/top_level.txt
geofetch-0.12.8.dist-info/RECORD
