Metadata-Version: 2.4
Name: geofetch
Version: 0.12.8
Summary: Downloads data and metadata from GEO and SRA and creates standard PEPs.
Home-page: https://github.com/pepkit/geofetch/
Author: Oleksandr Khoroshevskyi, Nathan Sheffield, Vince Reuter, Nathan LeRoy
License: BSD2
Keywords: project,bioinformatics,sequencing,ngs,workflow,GUI
Classifier: Development Status :: 4 - Beta
Classifier: License :: OSI Approved :: BSD License
Classifier: Programming Language :: Python :: 3.8
Classifier: Programming Language :: Python :: 3.9
Classifier: Programming Language :: Python :: 3.10
Classifier: Programming Language :: Python :: 3.11
Classifier: Programming Language :: Python :: 3.12
Classifier: Programming Language :: Python :: 3.13
Classifier: Topic :: Scientific/Engineering :: Bio-Informatics
License-File: LICENSE.txt
Requires-Dist: colorama>=0.3.9
Requires-Dist: logmuse>=0.2.6
Requires-Dist: ubiquerg>=0.6.2
Requires-Dist: requests>=2.28.1
Requires-Dist: xmltodict>=0.13.0
Requires-Dist: pandas>=1.5.3
Requires-Dist: peppy>=0.40.6
Requires-Dist: rich>=12.5.1
Requires-Dist: coloredlogs>=15.0.1
Requires-Dist: piper>=0.14.4
Dynamic: author
Dynamic: classifier
Dynamic: description
Dynamic: description-content-type
Dynamic: home-page
Dynamic: keywords
Dynamic: license
Dynamic: license-file
Dynamic: requires-dist
Dynamic: summary
